{
    "id": "05005ba741f06f85e2b263d0c670bfbf",
    "name": "Speaker Text",
    "description": null,
    "auth": null,
    "events": null,
    "variables": [],
    "order": [],
    "folders_order": [],
    "folders": [],
    "requests": [
        {
            "id": "0fb3e5a90cd5c96761afe0d7b4478e2a",
            "name": "Iniate Transcript",
            "url": "httpsapi.speakertext.com\/v1\/transcripts",
            "description": "This method is used to initiate one or more SpeakerText transcriptions.",
            "data": [],
            "dataMode": "raw",
            "headerData": null,
            "method": "post",
            "pathVariableData": [],
            "queryParams": [
                {
                    "key": "pingback_url",
                    "description": "If present, we will make a POST request to this URL upon transcript completion. The body of the request will have three keys: transcript_id (SpeakerTexts transcript id), ref_id (the media reference id or video id you specified in the original POST), and content (the HTML transcript for CaptionBox).",
                    "value": "",
                    "equals": true,
                    "enabled": true
                },
                {
                    "key": "sources",
                    "description": "(JSON) single source object or array of source objects",
                    "value": "",
                    "equals": true,
                    "enabled": true
                }
            ],
            "auth": null,
            "events": null,
            "folder": null,
            "protocolProfileBehavior": {
                "disableBodyPruning": true
            },
            "responses": [],
            "currentHelper": null,
            "helperAttributes": null,
            "collectionId": "05005ba741f06f85e2b263d0c670bfbf",
            "rawModeData": ""
        },
        {
            "id": "3ea44390e678d3a4156d3b9a65926fd1",
            "name": "Retrieve Transcription",
            "url": "httpsapi.speakertext.com\/v1\/transcripts\/{id}",
            "description": "This method is used to retrieve the results of SpeakerText transcriptions.",
            "data": [],
            "dataMode": "raw",
            "headerData": null,
            "method": "get",
            "pathVariableData": [],
            "queryParams": [
                {
                    "key": "format",
                    "description": "dfxp, srt, txt, xml, or html (for CaptionBox). When not specified, defaults to txt. Case-insensitive.",
                    "value": "",
                    "equals": true,
                    "enabled": true
                },
                {
                    "key": "id",
                    "description": "Transcript ID returned to you upon transcript creation",
                    "value": "",
                    "equals": true,
                    "enabled": true
                }
            ],
            "auth": null,
            "events": null,
            "folder": null,
            "protocolProfileBehavior": {
                "disableBodyPruning": true
            },
            "responses": [],
            "currentHelper": null,
            "helperAttributes": null,
            "collectionId": "05005ba741f06f85e2b263d0c670bfbf",
            "rawModeData": ""
        }
    ]
}